odoo/addons/sale_coupon_multi_use_currency/README.rst
odoo/addons/sale_coupon_multi_use_currency/__init__.py
odoo/addons/sale_coupon_multi_use_currency/__manifest__.py
odoo/addons/sale_coupon_multi_use_currency/i18n/fr.po
odoo/addons/sale_coupon_multi_use_currency/i18n/sale_coupon_multi_use_currency.pot
odoo/addons/sale_coupon_multi_use_currency/models/__init__.py
odoo/addons/sale_coupon_multi_use_currency/models/sale_coupon_program.py
odoo/addons/sale_coupon_multi_use_currency/readme/CONTRIBUTORS.rst
odoo/addons/sale_coupon_multi_use_currency/readme/DESCRIPTION.rst
odoo/addons/sale_coupon_multi_use_currency/static/description/icon.png
odoo/addons/sale_coupon_multi_use_currency/static/description/index.html
odoo/addons/sale_coupon_multi_use_currency/tests/__init__.py
odoo/addons/sale_coupon_multi_use_currency/tests/test_sale_coupon_use_currency.py
odoo13_addon_sale_coupon_multi_use_currency-13.0.1.0.1.dist-info/METADATA
odoo13_addon_sale_coupon_multi_use_currency-13.0.1.0.1.dist-info/WHEEL
odoo13_addon_sale_coupon_multi_use_currency-13.0.1.0.1.dist-info/top_level.txt
odoo13_addon_sale_coupon_multi_use_currency-13.0.1.0.1.dist-info/RECORD
